nece/__init__.py
nece/admin.py
nece/exceptions.py
nece/managers.py
nece/models.py
nece/tests.py
nece-0.8.2.dist-info/LICENSE
nece-0.8.2.dist-info/METADATA
nece-0.8.2.dist-info/WHEEL
nece-0.8.2.dist-info/top_level.txt
nece-0.8.2.dist-info/RECORD
