Metadata-Version: 2.1
Name: nece
Version: 0.8.2
Summary: A content translation framework using Postgresql's jsonb field in the background
Home-page: https://github.com/tatterdemalion/django-nece
Author: Can Mustafa Özdemir
Author-email: canmustafaozdemir@gmail.com
License: BSD License
Download-URL: https://github.com/tatterdemalion/django-nece/tarball/0.8.2
Keywords: translations,i18n,language,multilingual
Platform: UNKNOWN
Classifier: Framework :: Django
Classifier: Intended Audience :: Developers
Classifier: License :: OSI Approved :: BSD License
Classifier: Operating System :: OS Independent
Classifier: Programming Language :: Python :: 2.7
Classifier: Programming Language :: Python :: 3.4
Classifier: Programming Language :: Python :: 3.5
Classifier: Programming Language :: Python :: 3.6
Classifier: Programming Language :: Python :: 3.7
Classifier: Topic :: Database
Classifier: Topic :: Internet :: WWW/HTTP :: Dynamic Content
Classifier: Topic :: Text Processing :: Linguistic
Requires-Dist: Django (>=1.9)
Requires-Dist: six (>=1.10.0)
Provides-Extra: psycopg2
Requires-Dist: psycopg2 (>=2.8.1) ; extra == 'psycopg2'
Provides-Extra: psycopg2-binary
Requires-Dist: psycopg2-binary (>=2.8.1) ; extra == 'psycopg2-binary'
